__init__.py
benepar_nx/constituency_parse.py
benepar_nx-0.0.1.dist-info/LICENSE
benepar_nx-0.0.1.dist-info/METADATA
benepar_nx-0.0.1.dist-info/WHEEL
benepar_nx-0.0.1.dist-info/top_level.txt
benepar_nx-0.0.1.dist-info/RECORD
