Metadata-Version: 2.1
Name: benepar_nx
Version: 0.0.1
Summary: NetworkX graph from benepar constituency parse
Author-email: "y@wildfluss.com" <y@wildfluss.com>
Project-URL: Homepage, https://github.com/wildfluss/benepar_nx
Project-URL: Bug Tracker, https://github.com/wildfluss/benepar_nx/issues
Classifier: Programming Language :: Python :: 3
Classifier: License :: OSI Approved :: MIT License
Classifier: Operating System :: OS Independent
Requires-Python: >=3.11
License-File: LICENSE
